{
  "last_updated": "2026-04-26T15:58:53",
  "processed_files": {
    "J-ENG_UECC_Engines_USI-10004_9_2.pdf": {
      "processed_at": "2026-04-26T15:55:08",
      "file_size_bytes": 355765,
      "file_mtime": "2023-09-25T09:01:20",
      "sha256": "375a237097f4a08ee4d7d210de1db946f5106040c0168f2db1d29320ecadf0bb"
    },
    "WinGD_engine-oils_v18.pdf": {
      "processed_at": "2026-04-26T15:55:08",
      "file_size_bytes": 566329,
      "file_mtime": "2026-01-30T01:11:52",
      "sha256": "87d636d027faf3b3184d13942dcd631139347be71797f063e10c647de8f52641"
    }
  }
}